{"frames":{"wooden-shield.png":{"frame":{"x":2,"y":2,"w":587,"h":680},"rotated":false,"trimmed":true,"spriteSourceSize":{"x":47,"y":35,"w":587,"h":680},"sourceSize":{"w":672,"h":741}},"waterskin.png":{"frame":{"x":591,"y":2,"w":235,"h":335},"rotated":false,"trimmed":true,"spriteSourceSize":{"x":78,"y":28,"w":235,"h":335},"sourceSize":{"w":392,"h":392}},"wardens-plate.png":{"frame":{"x":2,"y":684,"w":540,"h":633},"rotated":true,"trimmed":true,"spriteSourceSize":{"x":81,"y":82,"w":540,"h":633},"sourceSize":{"w":699,"h":750}},"tower-shield.png":{"frame":{"x":828,"y":2,"w":517,"h":704},"rotated":false,"trimmed":true,"spriteSourceSize":{"x":72,"y":29,"w":517,"h":704},"sourceSize":{"w":637,"h":749}},"torso.png":{"frame":{"x":637,"y":708,"w":290,"h":270},"rotated":true,"trimmed":false,"spriteSourceSize":{"x":0,"y":0,"w":290,"h":270},"sourceSize":{"w":290,"h":270}},"torch.png":{"frame":{"x":637,"y":1000,"w":190,"h":392},"rotated":true,"trimmed":true,"spriteSourceSize":{"x":101,"y":0,"w":190,"h":392},"sourceSize":{"w":392,"h":392}},"tire-tread-sandals.png":{"frame":{"x":2,"y":1226,"w":372,"h":337},"rotated":false,"trimmed":true,"spriteSourceSize":{"x":31,"y":39,"w":372,"h":337},"sourceSize":{"w":451,"h":404}},"sword.png":{"frame":{"x":1031,"y":708,"w":294,"h":344},"rotated":false,"trimmed":false,"spriteSourceSize":{"x":0,"y":0,"w":294,"h":344},"sourceSize":{"w":294,"h":344}},"survivors-edge.png":{"frame":{"x":1347,"y":2,"w":693,"h":704},"rotated":false,"trimmed":true,"spriteSourceSize":{"x":32,"y":26,"w":693,"h":704},"sourceSize":{"w":765,"h":762}},"stim-pack.png":{"frame":{"x":1327,"y":708,"w":530,"h":565},"rotated":true,"trimmed":true,"spriteSourceSize":{"x":63,"y":96,"w":530,"h":565},"sourceSize":{"w":684,"h":738}},"steel-toe-boots.png":{"frame":{"x":376,"y":1240,"w":298,"h":248},"rotated":true,"trimmed":true,"spriteSourceSize":{"x":20,"y":39,"w":298,"h":248},"sourceSize":{"w":351,"h":324}},"steel-boots.png":{"frame":{"x":2,"y":1565,"w":694,"h":657},"rotated":false,"trimmed":true,"spriteSourceSize":{"x":51,"y":73,"w":694,"h":657},"sourceSize":{"w":759,"h":738}},"spear.png":{"frame":{"x":637,"y":1192,"w":341,"h":474},"rotated":true,"trimmed":false,"spriteSourceSize":{"x":0,"y":0,"w":341,"h":474},"sourceSize":{"w":341,"h":474}},"soggy-slippers.png":{"frame":{"x":698,"y":1535,"w":373,"h":304},"rotated":true,"trimmed":true,"spriteSourceSize":{"x":25,"y":57,"w":373,"h":304},"sourceSize":{"w":451,"h":404}},"shirt.png":{"frame":{"x":698,"y":1910,"w":284,"h":284},"rotated":false,"trimmed":true,"spriteSourceSize":{"x":54,"y":54,"w":284,"h":284},"sourceSize":{"w":392,"h":392}},"seedling.png":{"frame":{"x":637,"y":339,"w":155,"h":173},"rotated":true,"trimmed":true,"spriteSourceSize":{"x":42,"y":32,"w":155,"h":173},"sourceSize":{"w":239,"h":236}},"scrap.png":{"frame":{"x":637,"y":496,"w":199,"h":158},"rotated":true,"trimmed":true,"spriteSourceSize":{"x":20,"y":39,"w":199,"h":158},"sourceSize":{"w":239,"h":236}},"scrap-plate.png":{"frame":{"x":1004,"y":1535,"w":564,"h":634},"rotated":false,"trimmed":true,"spriteSourceSize":{"x":81,"y":34,"w":564,"h":634},"sourceSize":{"w":678,"h":714}},"scavenger-hood.png":{"frame":{"x":1113,"y":1240,"w":273,"h":291},"rotated":false,"trimmed":true,"spriteSourceSize":{"x":43,"y":39,"w":273,"h":291},"sourceSize":{"w":348,"h":353}},"rusted-helm.png":{"frame":{"x":1388,"y":1240,"w":288,"h":242},"rotated":true,"trimmed":true,"spriteSourceSize":{"x":30,"y":69,"w":288,"h":242},"sourceSize":{"w":348,"h":353}},"riot-visor.png":{"frame":{"x":1632,"y":1240,"w":302,"h":242},"rotated":false,"trimmed":true,"spriteSourceSize":{"x":26,"y":70,"w":302,"h":242},"sourceSize":{"w":348,"h":353}},"reinforced-waders.png":{"frame":{"x":1632,"y":1484,"w":321,"h":311},"rotated":false,"trimmed":true,"spriteSourceSize":{"x":48,"y":61,"w":321,"h":311},"sourceSize":{"w":451,"h":404}},"reinforced-vest.png":{"frame":{"x":2042,"y":2,"w":577,"h":704},"rotated":false,"trimmed":true,"spriteSourceSize":{"x":117,"y":11,"w":577,"h":704},"sourceSize":{"w":759,"h":732}},"potion.png":{"frame":{"x":1570,"y":1797,"w":281,"h":285},"rotated":false,"trimmed":true,"spriteSourceSize":{"x":55,"y":53,"w":281,"h":285},"sourceSize":{"w":392,"h":392}},"plated-shinwraps.png":{"frame":{"x":1853,"y":1797,"w":257,"h":301},"rotated":false,"trimmed":true,"spriteSourceSize":{"x":37,"y":11,"w":257,"h":301},"sourceSize":{"w":351,"h":324}},"obsidian-blade.png":{"frame":{"x":2,"y":2224,"w":730,"h":704},"rotated":false,"trimmed":true,"spriteSourceSize":{"x":135,"y":17,"w":730,"h":704},"sourceSize":{"w":906,"h":741}},"military-helmet.png":{"frame":{"x":1570,"y":2084,"w":306,"h":273},"rotated":true,"trimmed":true,"spriteSourceSize":{"x":11,"y":55,"w":306,"h":273},"sourceSize":{"w":347,"h":379}},"military-greaves.png":{"frame":{"x":2112,"y":708,"w":252,"h":278},"rotated":true,"trimmed":true,"spriteSourceSize":{"x":49,"y":19,"w":252,"h":278},"sourceSize":{"w":351,"h":324}},"metal-faceplate.png":{"frame":{"x":1894,"y":962,"w":256,"h":307},"rotated":true,"trimmed":true,"spriteSourceSize":{"x":37,"y":30,"w":256,"h":307},"sourceSize":{"w":332,"h":366}},"map.png":{"frame":{"x":2203,"y":962,"w":399,"h":393},"rotated":false,"trimmed":true,"spriteSourceSize":{"x":33,"y":34,"w":399,"h":393},"sourceSize":{"w":480,"h":470}},"makeshift-helmet.png":{"frame":{"x":1955,"y":1357,"w":348,"h":337},"rotated":true,"trimmed":true,"spriteSourceSize":{"x":0,"y":7,"w":348,"h":337},"sourceSize":{"w":348,"h":353}},"light-shard.png":{"frame":{"x":1894,"y":708,"w":185,"h":198},"rotated":true,"trimmed":true,"spriteSourceSize":{"x":27,"y":19,"w":185,"h":198},"sourceSize":{"w":239,"h":236}},"leather-tunic.png":{"frame":{"x":2294,"y":1357,"w":282,"h":310},"rotated":true,"trimmed":true,"spriteSourceSize":{"x":54,"y":41,"w":282,"h":310},"sourceSize":{"w":392,"h":392}},"leather-sneakers.png":{"frame":{"x":2294,"y":1641,"w":304,"h":216},"rotated":false,"trimmed":true,"spriteSourceSize":{"x":19,"y":66,"w":304,"h":216},"sourceSize":{"w":351,"h":324}},"knuckle-duster.png":{"frame":{"x":2112,"y":1859,"w":316,"h":322},"rotated":true,"trimmed":false,"spriteSourceSize":{"x":0,"y":0,"w":316,"h":322},"sourceSize":{"w":316,"h":322}},"knife.png":{"frame":{"x":1845,"y":2100,"w":211,"h":361},"rotated":false,"trimmed":true,"spriteSourceSize":{"x":90,"y":15,"w":211,"h":361},"sourceSize":{"w":392,"h":392}},"iron-helm.png":{"frame":{"x":984,"y":2171,"w":575,"h":704},"rotated":false,"trimmed":true,"spriteSourceSize":{"x":96,"y":26,"w":575,"h":704},"sourceSize":{"w":780,"h":753}},"inventory.png":{"frame":{"x":2621,"y":2,"w":780,"h":826},"rotated":false,"trimmed":false,"spriteSourceSize":{"x":0,"y":0,"w":780,"h":826},"sourceSize":{"w":780,"h":826}},"ichor.png":{"frame":{"x":1113,"y":1054,"w":143,"h":187},"rotated":true,"trimmed":true,"spriteSourceSize":{"x":48,"y":24,"w":143,"h":187},"sourceSize":{"w":239,"h":236}},"healing-potion.png":{"frame":{"x":1561,"y":2392,"w":281,"h":285},"rotated":false,"trimmed":true,"spriteSourceSize":{"x":55,"y":53,"w":281,"h":285},"sourceSize":{"w":392,"h":392}},"head.png":{"frame":{"x":734,"y":2196,"w":236,"h":272},"rotated":false,"trimmed":true,"spriteSourceSize":{"x":1,"y":0,"w":236,"h":272},"sourceSize":{"w":237,"h":272}},"hazmat-hood.png":{"frame":{"x":1844,"y":2463,"w":321,"h":342},"rotated":false,"trimmed":true,"spriteSourceSize":{"x":11,"y":25,"w":321,"h":342},"sourceSize":{"w":347,"h":379}},"hazmat-boots.png":{"frame":{"x":2058,"y":2177,"w":267,"h":286},"rotated":true,"trimmed":true,"spriteSourceSize":{"x":41,"y":22,"w":267,"h":286},"sourceSize":{"w":351,"h":324}},"gas-mask.png":{"frame":{"x":2346,"y":2177,"w":657,"h":693},"rotated":false,"trimmed":true,"spriteSourceSize":{"x":46,"y":23,"w":657,"h":693},"sourceSize":{"w":765,"h":747}},"fists.png":{"frame":{"x":2436,"y":1859,"w":256,"h":333},"rotated":true,"trimmed":false,"spriteSourceSize":{"x":0,"y":0,"w":256,"h":333},"sourceSize":{"w":256,"h":333}},"feet.png":{"frame":{"x":734,"y":2470,"w":240,"h":272},"rotated":false,"trimmed":false,"spriteSourceSize":{"x":0,"y":0,"w":240,"h":272},"sourceSize":{"w":240,"h":272}},"cultist-footwraps.png":{"frame":{"x":3005,"y":830,"w":249,"h":301},"rotated":true,"trimmed":true,"spriteSourceSize":{"x":47,"y":13,"w":249,"h":301},"sourceSize":{"w":351,"h":324}},"cult-mask.png":{"frame":{"x":3005,"y":1081,"w":288,"h":337},"rotated":true,"trimmed":true,"spriteSourceSize":{"x":37,"y":10,"w":288,"h":337},"sourceSize":{"w":348,"h":353}},"crossbow.png":{"frame":{"x":2,"y":2930,"w":856,"h":680},"rotated":false,"trimmed":true,"spriteSourceSize":{"x":75,"y":29,"w":856,"h":680},"sourceSize":{"w":1029,"h":768}},"coin.png":{"frame":{"x":2771,"y":830,"w":257,"h":228},"rotated":true,"trimmed":false,"spriteSourceSize":{"x":0,"y":0,"w":257,"h":228},"sourceSize":{"w":257,"h":228}},"cleaver.png":{"frame":{"x":860,"y":2877,"w":703,"h":691},"rotated":true,"trimmed":true,"spriteSourceSize":{"x":36,"y":30,"w":703,"h":691},"sourceSize":{"w":777,"h":750}},"ceremonial-toe-rings.png":{"frame":{"x":3005,"y":1371,"w":371,"h":313},"rotated":false,"trimmed":true,"spriteSourceSize":{"x":52,"y":66,"w":371,"h":313},"sourceSize":{"w":451,"h":404}},"bucket-head.png":{"frame":{"x":3005,"y":1686,"w":331,"h":365},"rotated":true,"trimmed":true,"spriteSourceSize":{"x":63,"y":29,"w":331,"h":365},"sourceSize":{"w":424,"h":423}},"bow.png":{"frame":{"x":3005,"y":2019,"w":295,"h":295},"rotated":false,"trimmed":false,"spriteSourceSize":{"x":0,"y":0,"w":295,"h":295},"sourceSize":{"w":295,"h":295}},"boots.png":{"frame":{"x":2604,"y":1089,"w":282,"h":261},"rotated":false,"trimmed":true,"spriteSourceSize":{"x":55,"y":65,"w":282,"h":261},"sourceSize":{"w":392,"h":392}},"bandana.png":{"frame":{"x":3005,"y":2316,"w":357,"h":347},"rotated":false,"trimmed":true,"spriteSourceSize":{"x":49,"y":34,"w":357,"h":347},"sourceSize":{"w":441,"h":410}},"arrow.png":{"frame":{"x":2606,"y":1352,"w":490,"h":156},"rotated":true,"trimmed":true,"spriteSourceSize":{"x":83,"y":241,"w":490,"h":156},"sourceSize":{"w":644,"h":644}},"antigen.png":{"frame":{"x":2604,"y":830,"w":141,"h":187},"rotated":false,"trimmed":true,"spriteSourceSize":{"x":48,"y":24,"w":141,"h":187},"sourceSize":{"w":239,"h":236}},"city-key.png":{"frame":{"x":2167,"y":2446,"w":169,"h":319},"rotated":false,"trimmed":true,"spriteSourceSize":{"x":110,"y":45,"w":169,"h":319},"sourceSize":{"w":400,"h":400}}},"animations":{},"meta":{"app":"http://github.com/pixijs/assetpack","version":"1.0","image":"items-2jo-7w.webp","format":"RGBA8888","size":{"w":3403,"h":3612},"scale":1,"related_multi_packs":[]}}