{"frames":{"main-menu.png":{"frame":{"x":2,"y":2,"w":1024,"h":1024},"rotated":false,"trimmed":false,"spriteSourceSize":{"x":0,"y":0,"w":1024,"h":1024},"sourceSize":{"w":1024,"h":1024}},"game-title.png":{"frame":{"x":1028,"y":2,"w":922,"h":772},"rotated":true,"trimmed":false,"spriteSourceSize":{"x":0,"y":0,"w":922,"h":772},"sourceSize":{"w":922,"h":772}}},"meta":{"app":"http://github.com/pixijs/assetpack","version":"1.0","image":"game-f5KDfA.png","format":"RGBA8888","size":{"w":1802,"h":1028},"scale":1,"related_multi_packs":[]}}