{"frames":{"skull.png":{"frame":{"x":2,"y":2,"w":337,"h":431},"rotated":false,"trimmed":false,"spriteSourceSize":{"x":0,"y":0,"w":337,"h":431},"sourceSize":{"w":337,"h":431}},"gas-man.png":{"frame":{"x":341,"y":2,"w":454,"h":393},"rotated":true,"trimmed":false,"spriteSourceSize":{"x":0,"y":0,"w":454,"h":393},"sourceSize":{"w":454,"h":393}},"face-2.png":{"frame":{"x":2,"y":458,"w":385,"h":431},"rotated":true,"trimmed":false,"spriteSourceSize":{"x":0,"y":0,"w":385,"h":431},"sourceSize":{"w":385,"h":431}},"face-1.png":{"frame":{"x":736,"y":2,"w":337,"h":433},"rotated":false,"trimmed":false,"spriteSourceSize":{"x":0,"y":0,"w":337,"h":433},"sourceSize":{"w":337,"h":433}},"face-0.png":{"frame":{"x":435,"y":458,"w":352,"h":433},"rotated":true,"trimmed":false,"spriteSourceSize":{"x":0,"y":0,"w":352,"h":433},"sourceSize":{"w":352,"h":433}}},"meta":{"app":"http://github.com/pixijs/assetpack","version":"1.0","image":"faces-vxkfEg.webp","format":"RGBA8888","size":{"w":1075,"h":845},"scale":1,"related_multi_packs":[]}}