{"frames":{"well-1.png":{"frame":{"x":2,"y":2,"w":319,"h":254},"rotated":false,"trimmed":true,"spriteSourceSize":{"x":107,"y":0,"w":319,"h":254},"sourceSize":{"w":450,"h":305}},"tent.png":{"frame":{"x":2,"y":258,"w":290,"h":265},"rotated":false,"trimmed":true,"spriteSourceSize":{"x":0,"y":14,"w":290,"h":265},"sourceSize":{"w":292,"h":293}},"ruin-wall-3.png":{"frame":{"x":323,"y":2,"w":239,"h":238},"rotated":true,"trimmed":true,"spriteSourceSize":{"x":116,"y":0,"w":239,"h":238},"sourceSize":{"w":457,"h":301}},"ruin-wall-2.png":{"frame":{"x":294,"y":258,"w":264,"h":211},"rotated":true,"trimmed":true,"spriteSourceSize":{"x":91,"y":4,"w":264,"h":211},"sourceSize":{"w":457,"h":277}},"ruin-wall-1.png":{"frame":{"x":2,"y":525,"w":249,"h":232},"rotated":false,"trimmed":true,"spriteSourceSize":{"x":114,"y":0,"w":249,"h":232},"sourceSize":{"w":459,"h":295}},"market-stall-1.png":{"frame":{"x":563,"y":2,"w":266,"h":266},"rotated":false,"trimmed":true,"spriteSourceSize":{"x":68,"y":0,"w":266,"h":266},"sourceSize":{"w":449,"h":305}},"campfire.png":{"frame":{"x":507,"y":270,"w":264,"h":264},"rotated":false,"trimmed":true,"spriteSourceSize":{"x":0,"y":14,"w":264,"h":264},"sourceSize":{"w":292,"h":293}},"building-3.png":{"frame":{"x":253,"y":536,"w":330,"h":219},"rotated":false,"trimmed":true,"spriteSourceSize":{"x":78,"y":0,"w":330,"h":219},"sourceSize":{"w":449,"h":296}},"building-2.png":{"frame":{"x":2,"y":759,"w":306,"h":257},"rotated":false,"trimmed":true,"spriteSourceSize":{"x":70,"y":0,"w":306,"h":257},"sourceSize":{"w":450,"h":298}},"building-1.png":{"frame":{"x":585,"y":536,"w":304,"h":198},"rotated":true,"trimmed":true,"spriteSourceSize":{"x":96,"y":27,"w":304,"h":198},"sourceSize":{"w":458,"h":273}}},"animations":{"building":["building-1.png","building-2.png","building-3.png"],"ruin-wall":["ruin-wall-1.png","ruin-wall-2.png","ruin-wall-3.png"]},"meta":{"app":"http://github.com/pixijs/assetpack","version":"1.0","image":"structures-2FFaGQ.webp","format":"RGBA8888","size":{"w":831,"h":1018},"scale":1,"related_multi_packs":[]}}